local.py
mcp_llm_client-0.1.2.dist-info/licenses/LICENSE
mcpclient/__init__.py
mcpclient/dev.py
mcpclient/api/api.py
mcpclient/api/auth/auth.py
mcpclient/api/routes/queries.py
mcpclient/config/llm_config.py
mcpclient/config/logger.py
mcpclient/mcp_manager/client.py
mcpclient/mcp_manager/servers.py
mcpclient/mcp_manager/connections/session_data.py
mcpclient/mcp_manager/services/service.py
mcpclient/services/llm/llm.py
mcpclient/services/llm/chat/chat.py
mcpclient/services/llm/chat/step.py
mcpclient/services/llm/models/google_service/claude.py
mcpclient/services/llm/models/openai_service/gpt.py
mcpclient/services/llm/prompts/system_prompts.py
mcpclient/services/llm/prompts/user_prompts.py
mcpclient/tools/clear_console.py
mcpclient/tools/get_uri_args.py
mcp_llm_client-0.1.2.dist-info/METADATA
mcp_llm_client-0.1.2.dist-info/WHEEL
mcp_llm_client-0.1.2.dist-info/top_level.txt
mcp_llm_client-0.1.2.dist-info/RECORD
