Metadata-Version: 2.4
Name: mcp-llm-client
Version: 0.1.2
Summary: Python client, based on fastmcp, for connecting to MCP servers through multiple protocols, specifically designed to work with integrated language models.
Author-email: Raúl Beltrán Gómez <rb58853@gmail.com>
License-Expression: MIT
Project-URL: Homepage, https://github.com/rb58853/mcp-llm-client
Project-URL: Issues, https://github.com/rb58853/mcp-llm-client/issues
Classifier: Programming Language :: Python :: 3
Classifier: Operating System :: OS Independent
Requires-Python: >=3.11
License-File: LICENSE
Requires-Dist: openai==1.68.2
Requires-Dist: mcp[cli]
Requires-Dist: mcp-oauth>=0.0.5
Dynamic: license-file
